pytopypi/__init__.py
pytopypi/pytopypi.py
pytopypi-0.0.2.dist-info/METADATA
pytopypi-0.0.2.dist-info/WHEEL
pytopypi-0.0.2.dist-info/top_level.txt
pytopypi-0.0.2.dist-info/RECORD
