Metadata-Version: 2.1
Name: pytopypi
Version: 0.0.2
Requires-Dist: logclshelper
Requires-Dist: syshelper
Requires-Dist: venvhelper
Requires-Dist: pytowhl
